MANIFEST.in
README.txt
cooking.theme-configure.zcml
setup.py
cooking/__init__.py
cooking.theme.egg-info/PKG-INFO
cooking.theme.egg-info/SOURCES.txt
cooking.theme.egg-info/dependency_links.txt
cooking.theme.egg-info/entry_points.txt
cooking.theme.egg-info/namespace_packages.txt
cooking.theme.egg-info/not-zip-safe
cooking.theme.egg-info/paster_plugins.txt
cooking.theme.egg-info/requires.txt
cooking.theme.egg-info/top_level.txt
cooking/theme/__init__.py
cooking/theme/adapters.py
cooking/theme/configure.zcml
cooking/theme/profiles.zcml
cooking/theme/setuphandlers.py
cooking/theme/skins.zcml
cooking/theme/tests.py
cooking/theme/version.txt
cooking/theme/browser/__init__.py
cooking/theme/browser/configure.zcml
cooking/theme/browser/interfaces.py
cooking/theme/browser/portlets.py
cooking/theme/browser/viewlet.pt
cooking/theme/browser/viewlets.py
cooking/theme/browser/images/README.txt
cooking/theme/browser/images/body_bg.jpg
cooking/theme/browser/images/contact.png
cooking/theme/browser/images/contact_bg.jpg
cooking/theme/browser/images/container_bg.jpg
cooking/theme/browser/images/header.jpg
cooking/theme/browser/images/menu_button.jpg
cooking/theme/browser/images/menu_hover.jpg
cooking/theme/browser/images/photo1.jpg
cooking/theme/browser/images/photo2.jpg
cooking/theme/browser/images/photo3.jpg
cooking/theme/browser/images/right_bg.jpg
cooking/theme/browser/stylesheets/README.txt
cooking/theme/browser/stylesheets/main.css
cooking/theme/browser/templates/footer.pt
cooking/theme/browser/templates/site_domain.pt
cooking/theme/browser/templates/site_header.pt
cooking/theme/browser/templates/site_title.pt
cooking/theme/init_data/check_code.pt
cooking/theme/init_data/contact_us_template.pt
cooking/theme/init_data/photo3.jpg
cooking/theme/init_data/welcome.pt
cooking/theme/locales/README.txt
cooking/theme/profiles/default/cooking.theme_various.txt
cooking/theme/profiles/default/cssregistry.xml
cooking/theme/profiles/default/jsregistry.xml
cooking/theme/profiles/default/metadata.xml
cooking/theme/profiles/default/skins.xml
cooking/theme/profiles/default/viewlets.xml
cooking/theme/skins/cooking_theme_custom_images/CONTENT.txt
cooking/theme/skins/cooking_theme_custom_templates/CONTENT.txt
cooking/theme/skins/cooking_theme_custom_templates/collection_details.pt
