Metadata-Version: 1.0
Name: cooking.theme
Version: 1.2.9
Summary: An installable theme for Plone 3
Home-page: http://svn.plone.org/svn/collective/
Author: Andriy Tomchuk
Author-email: njlytoh@gmail.com
License: GPL
Keywords: plone theme cooking
Platform: UNKNOWN
Classifier: Framework :: Plone
Classifier: Programming Language :: Python
